multipage.py
dash_multi-0.3.dist-info/LICENSE
dash_multi-0.3.dist-info/METADATA
dash_multi-0.3.dist-info/WHEEL
dash_multi-0.3.dist-info/top_level.txt
dash_multi-0.3.dist-info/RECORD
