Metadata-Version: 2.1
Name: dash-multi
Version: 0.3
Summary: a dash extension for multipage apps
Home-page: https://github.com/sjtrny/dash-multi
Author: Stephen Tierney
Author-email: sjtrny@gmail.com
License: UNKNOWN
Keywords: dash plotly multipage multi page
Platform: UNKNOWN
Classifier: License :: OSI Approved :: MIT License
Requires-Python: >=3
